double_click/__init__.py
double_click/click.py
double_click/markdown.py
double_click/models.py
double_click/request.py
double_click/user.py
double_click/utils.py
double_click-0.2.16.dist-info/LICENSE.txt
double_click-0.2.16.dist-info/METADATA
double_click-0.2.16.dist-info/WHEEL
double_click-0.2.16.dist-info/top_level.txt
double_click-0.2.16.dist-info/RECORD
