Metadata-Version: 2.1
Name: double-click
Version: 0.2.16
Summary: Helper framework to augment Click.
Home-page: https://github.com/WillNye/double_click
Author: Will Beasley
Author-email: willbeas88@gmail.com
License: UNKNOWN
Platform: UNKNOWN
Classifier: Programming Language :: Python
Classifier: Topic :: Software Development :: Libraries
Requires-Python: >=3.7
Requires-Dist: chardet (<4.0.0)
Requires-Dist: Click (<8.0,>=7.1.1)
Requires-Dist: colored (<2.0.0)
Requires-Dist: idna (<3.0)
Requires-Dist: Markdown (<4.0.0)
Requires-Dist: mdv3 (<3.0.0,>=2.0.0)
Requires-Dist: Pygments (<3.0.0)
Requires-Dist: pytest (<6.0.0)
Requires-Dist: pytest-cov (<3.0.0)
Requires-Dist: requests (<3.0.0)
Requires-Dist: tabulate (<1.0.0)
Requires-Dist: tqdm (<5.0.0)
